cueadmin/__init__.py
cueadmin/__main__.py
cueadmin/common.py
cueadmin/format.py
cueadmin/output.py
cueadmin/util.py
opencue_cueadmin-1.13.8.dist-info/METADATA
opencue_cueadmin-1.13.8.dist-info/WHEEL
opencue_cueadmin-1.13.8.dist-info/entry_points.txt
opencue_cueadmin-1.13.8.dist-info/RECORD
