Metadata-Version: 2.1
Name: opencue_cueadmin
Version: 1.13.8
Summary: CueAdmin is a command-line administration tool for OpenCue that provides full control over jobs, layers, frames, and hosts. It allows administrators to perform advanced management tasks such as setting priorities, killing jobs, or managing resource allocation.
Requires-Python: >3.7
Requires-Dist: opencue-pycue
Provides-Extra: dev
Requires-Dist: black; extra == 'dev'
Requires-Dist: isort; extra == 'dev'
Requires-Dist: mock==2.0.0; extra == 'dev'
Requires-Dist: pyfakefs==5.2.3; extra == 'dev'
Requires-Dist: pylint; extra == 'dev'
Requires-Dist: pytest; extra == 'dev'
Requires-Dist: pytest-cov; extra == 'dev'
Requires-Dist: pytest-mock; extra == 'dev'
Provides-Extra: test
Requires-Dist: mock==2.0.0; extra == 'test'
Requires-Dist: pyfakefs==5.2.3; extra == 'test'
Requires-Dist: pytest; extra == 'test'
Requires-Dist: pytest-cov; extra == 'test'
Requires-Dist: pytest-mock; extra == 'test'
